<?xml version="1.0"?>
<Results version="1.0">
<ReportNode type="testrun">
<ReportNode type="Iteration">
<ReportNode type="Action">
<ReportNode type="Step">
<Data>
    <Name>SystemUtil.Run "C:\Program Files\Google\Chrome\Application\chrome.exe",1</Name>
    <StartTime>2024-02-05 15:14:27</StartTime>
    <Result>Done</Result>
    <Extension>
      <IconKey>b72950d66c0c4a618246c0912e5135ae</IconKey>
      <IsPlainTextNodeName>True</IsPlainTextNodeName>
    </Extension>
    <DeviceInfo />
  </Data>
</ReportNode>
<ReportNode type="Step">
<Data>
    <Name>Stop Run</Name>
    <Description>Run stopped by user.</Description>
    <StartTime>2024-02-05 15:14:41</StartTime>
    <Result>Information</Result>
    <Extension>
      <IconKey>c86858a4c32740558fad99fd41d8c8dc</IconKey>
      <IsPlainTextNodeName>True</IsPlainTextNodeName>
    </Extension>
  </Data>
</ReportNode>
<Data>
    <Name>Action1</Name>
    <Description />
    <StartTime>2024-02-05 15:14:26</StartTime>
    <Duration>15</Duration>
    <Result>Done</Result>
    <InputParameters />
    <Extension>
      <IconKey>e9c3ae29696749fc938bcb9e8537cfda</IconKey>
      <IsPlainTextNodeName>True</IsPlainTextNodeName>
    </Extension>
  </Data>
</ReportNode>
<Data>
    <Name>Action0</Name>
    <Description />
    <StartTime>2024-02-05 15:14:26</StartTime>
    <Duration>15</Duration>
    <Result>Done</Result>
    <Extension>
      <IconKey>a8ea6e64173d4ef480caa9b9965c9e96</IconKey>
      <IsPlainTextNodeName>True</IsPlainTextNodeName>
    </Extension>
    <Index>1</Index>
    <TestedApplications />
  </Data>
</ReportNode>
<ReportNode type="Step">
<Data>
    <Name>Stop Run</Name>
    <Description>Run stopped by user.</Description>
    <StartTime>2024-02-05 15:14:41</StartTime>
    <Result>Information</Result>
    <Extension>
      <IconKey>8b56a11e2dd143a18f0c807a70c6caa7</IconKey>
      <IsPlainTextNodeName>True</IsPlainTextNodeName>
    </Extension>
  </Data>
</ReportNode>
<Data>
    <Name>WebTable</Name>
    <ToolName>Micro Focus UFT One</ToolName>
    <ToolVersion>2021</ToolVersion>
    <ToolVersionStringLiteral>2021</ToolVersionStringLiteral>
    <Description />
    <StartTime>2024-02-05 15:14:25</StartTime>
    <Duration>16</Duration>
    <Result>Done</Result>
    <InputParameters />
    <Extension>
      <IconKey>89c1c06a80e9422691f12f871f811f2e</IconKey>
      <IsPlainTextNodeName>True</IsPlainTextNodeName>
    </Extension>
    <Environment>
      <Timezone>+05:30:00</Timezone>
      <Locale>English (United States)</Locale>
      <User>ARDIANET\agadage</User>
      <CpuInfo>Intel(R) Core(TM) i5-8400T CPU @ 1.70GHz</CpuInfo>
      <NumberOfCores>6</NumberOfCores>
      <TotalMemory>8015</TotalMemory>
      <HostName>ardianet.net\D-INE-FWTG9R2</HostName>
      <OSInfo>Windows 10 22H2 (x64)</OSInfo>
    </Environment>
    <TestedApplications />
    <Links>
      <Link type="DataTable" reference="Default.xlsx" displayname="Default Data Table" />
    </Links>
  </Data>
</ReportNode>
<GeneralInfo>
    <ResultName>Res9</ResultName>
    <RunStartTime>2024-02-05 15:14:25</RunStartTime>
    <Timezone>+05:30:00</Timezone>
    <OrchestrationToolName>Micro Focus UFT One</OrchestrationToolName>
    <OrchestrationToolVersion>2021</OrchestrationToolVersion>
    <OrchestrationToolVersionStringLiteral>2021</OrchestrationToolVersionStringLiteral>
  </GeneralInfo>
</Results>