<?xml version="1.0"?>
<Results version="1.0">
<ReportNode type="testrun">
<ReportNode type="Iteration">
<ReportNode type="Action">
<Data>
    <Name>Action1</Name>
    <Description />
    <StartTime>2024-02-02 11:24:12</StartTime>
    <Result>Done</Result>
    <InputParameters />
    <Extension>
      <IconKey>6dc2b570e5d44e0081838d34c0bde92b</IconKey>
      <IsPlainTextNodeName>True</IsPlainTextNodeName>
    </Extension>
  </Data>
</ReportNode>
<Data>
    <Name>Action0</Name>
    <Description />
    <StartTime>2024-02-02 11:24:12</StartTime>
    <Duration>1</Duration>
    <Result>Done</Result>
    <Extension>
      <IconKey>d9d8cd48466847379e83d3c9acfa4b10</IconKey>
      <IsPlainTextNodeName>True</IsPlainTextNodeName>
    </Extension>
    <Index>1</Index>
    <TestedApplications />
  </Data>
</ReportNode>
<ReportNode type="Iteration">
<ReportNode type="Action">
<Data>
    <Name>Action1</Name>
    <Description />
    <StartTime>2024-02-02 11:24:13</StartTime>
    <Result>Done</Result>
    <InputParameters />
    <Extension>
      <IconKey>6dc2b570e5d44e0081838d34c0bde92b</IconKey>
      <IsPlainTextNodeName>True</IsPlainTextNodeName>
    </Extension>
  </Data>
</ReportNode>
<Data>
    <Name>Action0</Name>
    <Description />
    <StartTime>2024-02-02 11:24:13</StartTime>
    <Duration>0</Duration>
    <Result>Done</Result>
    <Extension>
      <IconKey>d9d8cd48466847379e83d3c9acfa4b10</IconKey>
      <IsPlainTextNodeName>True</IsPlainTextNodeName>
    </Extension>
    <Index>2</Index>
    <TestedApplications />
  </Data>
</ReportNode>
<Data>
    <Name>DataTable_Practice</Name>
    <ToolName>Micro Focus UFT One</ToolName>
    <ToolVersion>2021</ToolVersion>
    <ToolVersionStringLiteral>2021</ToolVersionStringLiteral>
    <Description />
    <StartTime>2024-02-02 11:24:10</StartTime>
    <Duration>3</Duration>
    <Result>Done</Result>
    <InputParameters />
    <Extension>
      <IconKey>a77ea93c37d74e838fda067a8d491cb8</IconKey>
      <IsPlainTextNodeName>True</IsPlainTextNodeName>
    </Extension>
    <Environment>
      <Timezone>+05:30:00</Timezone>
      <Locale>English (United States)</Locale>
      <User>ARDIANET\agadage</User>
      <CpuInfo>Intel(R) Core(TM) i5-8400T CPU @ 1.70GHz</CpuInfo>
      <NumberOfCores>6</NumberOfCores>
      <TotalMemory>8015</TotalMemory>
      <HostName>ardianet.net\D-INE-FWTG9R2</HostName>
      <OSInfo>Windows 10 22H2 (x64)</OSInfo>
    </Environment>
    <TestedApplications />
    <Links>
      <Link type="DataTable" reference="Default.xlsx" displayname="Default Data Table" />
    </Links>
  </Data>
</ReportNode>
<GeneralInfo>
    <ResultName>Res19</ResultName>
    <RunStartTime>2024-02-02 11:24:10</RunStartTime>
    <Timezone>+05:30:00</Timezone>
    <OrchestrationToolName>Micro Focus UFT One</OrchestrationToolName>
    <OrchestrationToolVersion>2021</OrchestrationToolVersion>
    <OrchestrationToolVersionStringLiteral>2021</OrchestrationToolVersionStringLiteral>
  </GeneralInfo>
</Results>